[
  {
    "file": "1224861124.PDF",
    "stock_code": "300995",
    "stock_name": "奇德新材",
    "stage": "定增",
    "doc_type": "定增",
    "content": "{\n  \"股票名称\": \"奇德新材\",\n  \"股票代码\": \"300995\",\n  \"公告日期\": \"\",\n  \"预计完成日期\": \"\",\n  \"解禁日期\": \"\",\n  \"股份详情\": \"向特定对象发行A股股票数量不超过25,039,170股，占发行前剔除库存股后股本总额的30%\",\n  \"每股价格\": \"发行价格不低于定价基准日前二十个交易日公司股票交易均价的80%（询价确定）元\",\n  \"总金额\": \"2.8亿元\",\n  \"总占比数\": \"不超过发行前剔除库存股后股本总额的30%\",\n  \"转让方信息\": \"广东奇德新材料股份有限公司\",\n  \"受让方信息\": \"不超过35名符合规定条件的特定投资者（证券投资基金管理公司、证券公司、信托公司、财务公司、保险机构投资者、合格境外机构投资者、人民币合格境外机构投资者以及符合法律法规条件的法人投资者、自然人投资者或机构投资者）\"\n}",
    "_parsed": {
      "股票名称": "奇德新材",
      "股票代码": "300995",
      "公告日期": "",
      "预计完成日期": "",
      "解禁日期": "",
      "股份详情": "向特定对象发行A股股票数量不超过25,039,170股，占发行前剔除库存股后股本总额的30%",
      "每股价格": "发行价格不低于定价基准日前二十个交易日公司股票交易均价的80%（询价确定）元",
      "总金额": "2.8亿元",
      "总占比数": "不超过发行前剔除库存股后股本总额的30%",
      "转让方信息": "广东奇德新材料股份有限公司",
      "受让方信息": "不超过35名符合规定条件的特定投资者（证券投资基金管理公司、证券公司、信托公司、财务公司、保险机构投资者、合格境外机构投资者、人民币合格境外机构投资者以及符合法律法规条件的法人投资者、自然人投资者或机构投资者）"
    },
    "_price": "发行价格不低于定价基准日前二十个交易日公司股票交易均价的80%（询价确定）元",
    "_announce_date": "",
    "_est_finish_date": "",
    "_unlock_date": "",
    "_transferor": "广东奇德新材料股份有限公司",
    "_recipients_short": "不超过35名符合规定条件的特定投资者（证券投资基金管理公司、证券公司、信托公司...",
    "_recipients_full": "不超过35名符合规定条件的特定投资者（证券投资基金管理公司、证券公司、信托公司、财务公司、保险机构投资者、合格境外机构投资者、人民币合格境外机构投资者以及符合法律法规条件的法人投资者、自然人投资者或机构投资者）"
  },
  {
    "file": "1224858670.PDF",
    "stock_code": "000159",
    "stock_name": "国际实业",
    "stage": "定增",
    "doc_type": "定增",
    "content": "{\n  \"股票名称\": \"国际实业\",\n  \"股票代码\": \"000159\",\n  \"公告日期\": \"2025-09-25\",\n  \"预计完成日期\": \"2025-09-25\",\n  \"解禁日期\": \"2028-09-25\",\n  \"股份详情\": \"向特定对象非公开发行不超过144,205,797股A股，占发行前总股本不超过30%，募集资金用于补充流动资金\",\n  \"每股价格\": \"4.59元\",\n  \"总金额\": \"6.6亿元\",\n  \"总占比数\": \"不超过30%\",\n  \"转让方信息\": \"新疆国际实业股份有限公司\",\n  \"受让方信息\": \"新疆融能投资发展有限公司\"\n}",
    "_parsed": {
      "股票名称": "国际实业",
      "股票代码": "000159",
      "公告日期": "2025-09-25",
      "预计完成日期": "2025-09-25",
      "解禁日期": "2028-09-25",
      "股份详情": "向特定对象非公开发行不超过144,205,797股A股，占发行前总股本不超过30%，募集资金用于补充流动资金",
      "每股价格": "4.59元",
      "总金额": "6.6亿元",
      "总占比数": "不超过30%",
      "转让方信息": "新疆国际实业股份有限公司",
      "受让方信息": "新疆融能投资发展有限公司"
    },
    "_price": "4.59元",
    "_announce_date": "2025-09-25",
    "_est_finish_date": "2025-09-25",
    "_unlock_date": "2028-09-25",
    "_transferor": "新疆国际实业股份有限公司",
    "_recipients_short": "新疆融能投资发展有限公司",
    "_recipients_full": "新疆融能投资发展有限公司"
  }
]